minesweeper/__init__.py
minesweeper/game.py
minesweeper/minesweeper.py
minesweeper/minesweeper_ai.py
minesweeper/minesweeper_cli.py
minesweeper/renderer.py
minesweeper/test_minesweeper.py
pmine-1.0.4.dist-info/LICENSE
pmine-1.0.4.dist-info/METADATA
pmine-1.0.4.dist-info/WHEEL
pmine-1.0.4.dist-info/entry_points.txt
pmine-1.0.4.dist-info/top_level.txt
pmine-1.0.4.dist-info/RECORD
