Metadata-Version: 2.1
Name: pmine
Version: 1.0.4
Summary: Terminal based Minesweeper using curses. Includes a self playing AI.
Home-page: https://github.com/kindjie/minesweeper
Author: Owen Wiggins
Author-email: o@owx.dev
License: UNKNOWN
Project-URL: Bug Tracker, https://github.com/kindjie/minesweeper/issues
Keywords: minesweeper game cli curses
Platform: UNKNOWN
Classifier: Programming Language :: Python :: 2.7
Classifier: Programming Language :: Python :: 3.6
Classifier: Environment :: Console :: Curses
Classifier: Development Status :: 5 - Production/Stable
Classifier: Intended Audience :: End Users/Desktop
Classifier: License :: OSI Approved :: MIT License
Classifier: Natural Language :: English
Classifier: Operating System :: OS Independent
Classifier: Topic :: Games/Entertainment
Requires-Python: >=2.7,>=3.6
License-File: LICENSE
